open_mpic_core/__about__.py
open_mpic_core/__init__.py
open_mpic_core/common_domain/check_parameters.py
open_mpic_core/common_domain/check_request.py
open_mpic_core/common_domain/check_response.py
open_mpic_core/common_domain/check_response_details.py
open_mpic_core/common_domain/validation_error.py
open_mpic_core/common_domain/enum/certificate_type.py
open_mpic_core/common_domain/enum/check_type.py
open_mpic_core/common_domain/enum/dcv_validation_method.py
open_mpic_core/common_domain/enum/dns_record_type.py
open_mpic_core/common_domain/enum/regional_internet_registry.py
open_mpic_core/common_domain/enum/url_scheme.py
open_mpic_core/common_domain/messages/ErrorMessages.py
open_mpic_core/common_util/domain_encoder.py
open_mpic_core/common_util/trace_level_logger.py
open_mpic_core/mpic_caa_checker/mpic_caa_checker.py
open_mpic_core/mpic_coordinator/cohort_creator.py
open_mpic_core/mpic_coordinator/mpic_coordinator.py
open_mpic_core/mpic_coordinator/mpic_request_validation_issue.py
open_mpic_core/mpic_coordinator/mpic_request_validator.py
open_mpic_core/mpic_coordinator/mpic_response_builder.py
open_mpic_core/mpic_coordinator/domain/mpic_orchestration_parameters.py
open_mpic_core/mpic_coordinator/domain/mpic_request.py
open_mpic_core/mpic_coordinator/domain/mpic_request_errors.py
open_mpic_core/mpic_coordinator/domain/mpic_response.py
open_mpic_core/mpic_coordinator/domain/perspective_response.py
open_mpic_core/mpic_coordinator/domain/remote_check_call_configuration.py
open_mpic_core/mpic_coordinator/domain/remote_check_exception.py
open_mpic_core/mpic_coordinator/domain/remote_perspective.py
open_mpic_core/mpic_coordinator/messages/mpic_request_validation_messages.py
open_mpic_core/mpic_dcv_checker/dcv_tls_alpn_validator.py
open_mpic_core/mpic_dcv_checker/dcv_utils.py
open_mpic_core/mpic_dcv_checker/mpic_dcv_checker.py
open_mpic_core_test/test_util/mock_dns_object_creator.py
open_mpic_core_test/test_util/valid_check_creator.py
open_mpic_core-6.3.0.dist-info/METADATA
open_mpic_core-6.3.0.dist-info/WHEEL
open_mpic_core-6.3.0.dist-info/licenses/LICENSE
open_mpic_core-6.3.0.dist-info/RECORD
