Metadata-Version: 2.4
Name: open-mpic-core
Version: 6.3.0
Summary: Library of core (common) MPIC functionality for Open MPIC in Python.
Project-URL: Documentation, https://github.com/open-mpic/open-mpic-core-python
Project-URL: Issues, https://github.com/open-mpic/open-mpic-core-python/issues
Project-URL: Source, https://github.com/open-mpic/open-mpic-core-python
Author-email: Henry Birge-Lee <henrybirgelee@gmail.com>, Grace Cimaszewski <ghc2@princeton.edu>, Dmitry Sharkov <dmitry.sharkov@sectigo.com>
License-Expression: MIT
License-File: LICENSE
Classifier: Development Status :: 4 - Beta
Classifier: Programming Language :: Python
Classifier: Programming Language :: Python :: 3.11
Classifier: Programming Language :: Python :: Implementation :: CPython
Classifier: Programming Language :: Python :: Implementation :: PyPy
Requires-Python: >=3.11
Requires-Dist: aiohttp==3.13.3
Requires-Dist: black==25.1.0
Requires-Dist: cryptography==45.0.4
Requires-Dist: dnspython==2.7.0
Requires-Dist: pydantic==2.11.7
Requires-Dist: pyyaml==6.0.2
Requires-Dist: requests==2.32.4
Provides-Extra: test
Requires-Dist: pytest-asyncio==1.0.0; extra == 'test'
Requires-Dist: pytest-cov==6.2.1; extra == 'test'
Requires-Dist: pytest-html==4.1.1; extra == 'test'
Requires-Dist: pytest-mock==3.14.1; extra == 'test'
Requires-Dist: pytest-profiling==1.8.1; extra == 'test'
Requires-Dist: pytest==8.4.1; extra == 'test'
